django_related_models/__init__.py
django_related_models/related_models.py
django_related_models-0.1.1.dist-info/AUTHORS.rst
django_related_models-0.1.1.dist-info/LICENSE
django_related_models-0.1.1.dist-info/METADATA
django_related_models-0.1.1.dist-info/WHEEL
django_related_models-0.1.1.dist-info/top_level.txt
django_related_models-0.1.1.dist-info/RECORD
